historylinks/__init__.py
historylinks/apps.py
historylinks/middleware.py
historylinks/models.py
historylinks/registration.py
historylinks/shortcuts.py
historylinks/management/__init__.py
historylinks/management/commands/__init__.py
historylinks/management/commands/buildhistorylinks.py
historylinks/migrations/0001_initial.py
historylinks/migrations/__init__.py
django_historylinks-1.1.4.dist-info/LICENSE
django_historylinks-1.1.4.dist-info/METADATA
django_historylinks-1.1.4.dist-info/WHEEL
django_historylinks-1.1.4.dist-info/top_level.txt
django_historylinks-1.1.4.dist-info/RECORD
