Metadata-Version: 2.1
Name: django-historylinks
Version: 1.1.4
Summary: Automatic SEO-friendly HTTP 301 redirects if the URL of a Django model changes.
Home-page: http://github.com/etianen/django-historylinks
Author: Dave Hall
Author-email: dave@etianen.com
Classifier: Development Status :: 5 - Production/Stable
Classifier: Environment :: Web Environment
Classifier: Intended Audience :: Developers
Classifier: License :: OSI Approved :: BSD License
Classifier: Operating System :: OS Independent
Classifier: Programming Language :: Python
Classifier: Framework :: Django
License-File: LICENSE
Requires-Dist: django (>=3.2)
Provides-Extra: test
Requires-Dist: coverage ; extra == 'test'
